{
  "id": "task-complete-api",
  "category": "API",
  "title": "Task Completion API Endpoint",
  "description": "Server action for completing tasks with automatic time tracking. Updates task status to done and records completion timestamp in KitchenTaskProgress.",
  "status": "backlog",
  "priority": 1,
  "complexity": "moderate",
  "dependencies": [
    "tenant-scoped-task-queries",
    "task-state-transition-logic"
  ],
  "createdAt": "2026-01-17T17:54:44.420Z",
  "updatedAt": "2026-01-17T19:17:56.058Z",
  "branchName": "preview",
  "descriptionHistory": [],
  "startedAt": "2026-01-17T19:17:48.983Z"
}